Metadata-Version: 2.1
Name: pmaxform3
Version: 0.14.1
Summary: A Python package to create XForms for ODK Collect.
Home-page: http://pypi.python.org/pypi/pyxform/
Author: github.com/xlsform
Author-email: info@xlsform.org
License: UNKNOWN
Platform: UNKNOWN
Requires-Dist: xlrd (>=1.1.0)
Requires-Dist: unicodecsv (>=0.14.1)
Requires-Dist: formencode
Requires-Dist: unittest2
Requires-Dist: functools32 (==3.2.3.post2) ; python_version < "3.2"
